[
    {
        "mValue":0.4,
        "mTitle":"原图",
        "type":2,
        "ratio":1,
        "strValue":"origin"
    },
    {
        "mValue":0.4,
        "mTitle":"自然1",
        "type":2,
        "ratio":1,
        "strValue":"ziran1"
    },
    {
        "mValue":0.4,
        "mTitle":"自然2",
        "type":2,
        "ratio":1,
        "strValue":"ziran2"
    },
    {
        "mValue":0.4,
        "mTitle":"自然3",
        "type":2,
        "ratio":1,
        "strValue":"ziran3"
    },
    {
        "mValue":0.4,
        "mTitle":"自然4",
        "type":2,
        "ratio":1,
        "strValue":"ziran4"
    },
    {
        "mValue":0.4,
        "mTitle":"自然5",
        "type":2,
        "ratio":1,
        "strValue":"ziran5"
    },
    {
        "mValue":0.4,
        "mTitle":"自然6",
        "type":2,
        "ratio":1,
        "strValue":"ziran6"
    },
    {
        "mValue":0.4,
        "mTitle":"自然7",
        "type":2,
        "ratio":1,
        "strValue":"ziran7"
    },
    {
        "mValue":0.4,
        "mTitle":"自然8",
        "type":2,
        "ratio":1,
        "strValue":"ziran8"
    },
    {
        "mValue":0.4,
        "mTitle":"质感灰1",
        "type":2,
        "ratio":1,
        "strValue":"zhiganhui1"
    },
    {
        "mValue":0.4,
        "mTitle":"质感灰2",
        "type":2,
        "ratio":1,
        "strValue":"zhiganhui2"
    },
    {
        "mValue":0.4,
        "mTitle":"质感灰3",
        "type":2,
        "ratio":1,
        "strValue":"zhiganhui3"
    },
    {
        "mValue":0.4,
        "mTitle":"质感灰4",
        "type":2,
        "ratio":1,
        "strValue":"zhiganhui4"
    },
    {
        "mValue":0.4,
        "mTitle":"质感灰5",
        "type":2,
        "ratio":1,
        "strValue":"zhiganhui5"
    },
    {
        "mValue":0.4,
        "mTitle":"质感灰6",
        "type":2,
        "ratio":1,
        "strValue":"zhiganhui6"
    },
    {
        "mValue":0.4,
        "mTitle":"质感灰7",
        "type":2,
        "ratio":1,
        "strValue":"zhiganhui7"
    },
    {
        "mValue":0.4,
        "mTitle":"质感灰8",
        "type":2,
        "ratio":1,
        "strValue":"zhiganhui8"
    },
    {
        "mValue":0.4,
        "mTitle":"蜜桃1",
        "type":2,
        "ratio":1,
        "strValue":"mitao1"
    },
    {
        "mValue":0.4,
        "mTitle":"蜜桃2",
        "type":2,
        "ratio":1,
        "strValue":"mitao2"
    },
    {
        "mValue":0.4,
        "mTitle":"蜜桃3",
        "type":2,
        "ratio":1,
        "strValue":"mitao3"
    },
    {
        "mValue":0.4,
        "mTitle":"蜜桃4",
        "type":2,
        "ratio":1,
        "strValue":"mitao4"
    },
    {
        "mValue":0.4,
        "mTitle":"蜜桃5",
        "type":2,
        "ratio":1,
        "strValue":"mitao5"
    },
    {
        "mValue":0.4,
        "mTitle":"蜜桃6",
        "type":2,
        "ratio":1,
        "strValue":"mitao6"
    },
    {
        "mValue":0.4,
        "mTitle":"蜜桃7",
        "type":2,
        "ratio":1,
        "strValue":"mitao7"
    },
    {
        "mValue":0.4,
        "mTitle":"蜜桃8",
        "type":2,
        "ratio":1,
        "strValue":"mitao8"
    },
    {
        "mValue":0.4,
        "mTitle":"白亮1",
        "type":2,
        "ratio":1,
        "strValue":"bailiang1"
    },
    {
        "mValue":0.4,
        "mTitle":"白亮2",
        "type":2,
        "ratio":1,
        "strValue":"bailiang2"
    },
    {
        "mValue":0.4,
        "mTitle":"白亮3",
        "type":2,
        "ratio":1,
        "strValue":"bailiang3"
    },
    {
        "mValue":0.4,
        "mTitle":"白亮4",
        "type":2,
        "ratio":1,
        "strValue":"bailiang4"
    },
    {
        "mValue":0.4,
        "mTitle":"白亮5",
        "type":2,
        "ratio":1,
        "strValue":"bailiang5"
    },
    {
        "mValue":0.4,
        "mTitle":"白亮6",
        "type":2,
        "ratio":1,
        "strValue":"bailiang6"
    },
    {
        "mValue":0.4,
        "mTitle":"白亮7",
        "type":2,
        "ratio":1,
        "strValue":"bailiang7"
    },
    {
        "mValue":0.4,
        "mTitle":"粉嫩1",
        "type":2,
        "ratio":1,
        "strValue":"fennen1"
    },
    {
        "mValue":0.4,
        "mTitle":"粉嫩2",
        "type":2,
        "ratio":1,
        "strValue":"fennen2"
    },
    {
        "mValue":0.4,
        "mTitle":"粉嫩3",
        "type":2,
        "ratio":1,
        "strValue":"fennen3"
    },
    {
        "mValue":0.4,
        "mTitle":"粉嫩5",
        "type":2,
        "ratio":1,
        "strValue":"fennen5"
    },
    {
        "mValue":0.4,
        "mTitle":"粉嫩6",
        "type":2,
        "ratio":1,
        "strValue":"fennen6"
    },
    {
        "mValue":0.4,
        "mTitle":"粉嫩7",
        "type":2,
        "ratio":1,
        "strValue":"fennen7"
    },
    {
        "mValue":0.4,
        "mTitle":"粉嫩8",
        "type":2,
        "ratio":1,
        "strValue":"fennen8"
    },
    {
        "mValue":0.4,
        "mTitle":"冷色调1",
        "type":2,
        "ratio":1,
        "strValue":"lengsediao1"
    },
    {
        "mValue":0.4,
        "mTitle":"冷色调2",
        "type":2,
        "ratio":1,
        "strValue":"lengsediao2"
    },
    {
        "mValue":0.4,
        "mTitle":"冷色调3",
        "type":2,
        "ratio":1,
        "strValue":"lengsediao3"
    },
    {
        "mValue":0.4,
        "mTitle":"冷色调4",
        "type":2,
        "ratio":1,
        "strValue":"lengsediao4"
    },
    {
        "mValue":0.4,
        "mTitle":"冷色调7",
        "type":2,
        "ratio":1,
        "strValue":"lengsediao7"
    },
    {
        "mValue":0.4,
        "mTitle":"冷色调8",
        "type":2,
        "ratio":1,
        "strValue":"lengsediao8"
    },
    {
        "mValue":0.4,
        "mTitle":"冷色调11",
        "type":2,
        "ratio":1,
        "strValue":"lengsediao11"
    },
    {
        "mValue":0.4,
        "mTitle":"暖色调1",
        "type":2,
        "ratio":1,
        "strValue":"nuansediao1"
    },
    {
        "mValue":0.4,
        "mTitle":"暖色调2",
        "type":2,
        "ratio":1,
        "strValue":"nuansediao2"
    },
    {
        "mValue":0.4,
        "mTitle":"个性1",
        "type":2,
        "ratio":1,
        "strValue":"gexing1"
    },
    {
        "mValue":0.4,
        "mTitle":"个性2",
        "type":2,
        "ratio":1,
        "strValue":"gexing2"
    },
    {
        "mValue":0.4,
        "mTitle":"个性3",
        "type":2,
        "ratio":1,
        "strValue":"gexing3"
    },
    {
        "mValue":0.4,
        "mTitle":"个性4",
        "type":2,
        "ratio":1,
        "strValue":"gexing4"
    },
    {
        "mValue":0.4,
        "mTitle":"个性5",
        "type":2,
        "ratio":1,
        "strValue":"gexing5"
    },
    {
        "mValue":0.4,
        "mTitle":"个性7",
        "type":2,
        "ratio":1,
        "strValue":"gexing7"
    },
    {
        "mValue":0.4,
        "mTitle":"个性10",
        "type":2,
        "ratio":1,
        "strValue":"gexing10"
    },
    {
        "mValue":0.4,
        "mTitle":"个性11",
        "type":2,
        "ratio":1,
        "strValue":"gexing11"
    },
    {
        "mValue":0.4,
        "mTitle":"小清新1",
        "type":2,
        "ratio":1,
        "strValue":"xiaoqingxin1"
    },
    {
        "mValue":0.4,
        "mTitle":"小清新3",
        "type":2,
        "ratio":1,
        "strValue":"xiaoqingxin3"
    },
    {
        "mValue":0.4,
        "mTitle":"小清新4",
        "type":2,
        "ratio":1,
        "strValue":"xiaoqingxin4"
    },
    {
        "mValue":0.4,
        "mTitle":"小清新6",
        "type":2,
        "ratio":1,
        "strValue":"xiaoqingxin6"
    },
    {
        "mValue":0.4,
        "mTitle":"黑白1",
        "type":2,
        "ratio":1,
        "strValue":"heibai1"
    },
    {
        "mValue":0.4,
        "mTitle":"黑白2",
        "type":2,
        "ratio":1,
        "strValue":"heibai2"
    },
    {
        "mValue":0.4,
        "mTitle":"黑白3",
        "type":2,
        "ratio":1,
        "strValue":"heibai3"
    },
    {
        "mValue":0.4,
        "mTitle":"黑白4",
        "type":2,
        "ratio":1,
        "strValue":"heibai4"
    }
]
